<?xml version="1.0" encoding="utf-8" ?>
<Defs>

  <IncidentDef>
    <defName>KhorneFrenzy</defName>
    <label>Frenzy of the Blood God</label>
    <targetTags>
      <li>Map_PlayerHome</li>
    </targetTags>
    <workerClass>Corruption.Worship.Wonders.IncidentWorker_KhorneFrenzy</workerClass>
    <baseChance>0.0</baseChance>
    <minRefireDays>99999</minRefireDays>
    <category>ThreatBig</category>
    <pointsScaleable>true</pointsScaleable>
    <ignoreConfigErrors>true</ignoreConfigErrors>
  
</IncidentDef>

  <IncidentDef>
    <defName>SlaaneshOrgy</defName>
    <label>Slaneeshian Orgy</label>
    <targetTags>
      <li>Map_PlayerHome</li>
    </targetTags>
    <workerClass>Corruption.Worship.Wonders.IncidentWorker_SlaaneshOrgy</workerClass>
    <category>ThreatSmall</category>
    <baseChance>0.0</baseChance>
    <pointsScaleable>false</pointsScaleable>
    <ignoreConfigErrors>true</ignoreConfigErrors>
  </IncidentDef>

  <IncidentDef>
    <defName>NurgleBreath</defName>
    <label>Breath of Nurgle</label>
    <workerClass>IncidentWorker_DiseaseHuman</workerClass>
    <letterLabel>Disease: Flu</letterLabel>
    <category>DiseaseHuman</category>
    <targetTags>
      <li>Map_PlayerHome</li>
      <li>Map_TempIncident</li>
      <li>Map_Misc</li>
      <li>Map_RaidBeacon</li>
      <li>Caravan</li>
    </targetTags>
    <diseaseIncident>Flu</diseaseIncident>
    <diseaseVictimFractionRange>
      <min>0.2</min>
      <max>0.5</max>
    </diseaseVictimFractionRange>
    <baseChance>0.0</baseChance>
    <ignoreConfigErrors>true</ignoreConfigErrors>
  </IncidentDef>
</Defs>